{
  "prefs": {
    "ScrollReportingEnabled": "false",
    "AliasExpansionEnabled": "false",
    "WelcomeTipsFeaturesUsed": "[{\"Action\":\"ThemePicker\"},{\"Action\":\"CommandSearch\"},{\"Hint\":\"CreateBlock\"},{\"Hint\":\"BlockSelect\"},{\"Action\":\"SplitPane\"}]",
    "HasAutoOpenedWelcomeFolder": "true",
    "SnackbarEnabled": "true",
    "ExtraMetaKeys": "{\"left_alt\":true,\"right_alt\":true}",
    "FontSize": "12.0",
    "SameLinePromptBlockState": "\"DoNotShow\"",
    "AIAutoDetectionEnabled": "false",
    "SavedPrompt": "\"Default\"",
    "HonorPS1": "false",
    "ReferralThemeActive": "true",
    "Notifications": "{\"mode\":\"Enabled\",\"is_long_running_enabled\":true,\"long_running_threshold\":{\"secs\":30,\"nanos\":0},\"is_password_prompt_enabled\":true}",
    "ExperimentId": "03616a92-be7e-42b9-922c-091f55c1928c",
    "InputAutodetectionBannerDismissed": "true",
    "CompletionsOpenWhileTyping": "false",
    "CrashReportingEnabled": "true",
    "UseAudibleBell": "true",
    "AIAssistantRequestLimitInfo": "{\"limit\":100,\"num_requests_used_since_refresh\":0,\"next_refresh_time\":\"2024-10-24T19:42:46.874979Z\",\"is_unlimited\":false}",
    "OverrideOpacity": "100",
    "TelemetryEnabled": "false",
    "AgentModeOnboardingBlockShown": "true",
    "NotebookFontSize": "14.0",
    "Theme": "{\"Custom\":{\"name\":\"Kanagawa\",\"path\":\"/home/araujo/.local/share/warp-terminal/themes/kanagawa.yml\"}}",
    "StartupShellOverride": "\"fish\"",
    "FontName": "\"JetBrains Mono\"",
    "VimModeEnabled": "true",
    "ChangelogVersions": "{\"v0.2024.09.17.08.02.stable_01\":true,\"v0.2024.09.24.08.02.stable_01\":true,\"v0.2024.10.15.08.02.stable_03\":true,\"v0.2024.10.15.08.02.stable_04\":true,\"v0.2024.10.23.14.49.stable_00\":true,\"v0.2024.10.29.08.02.stable_02\":true,\"v0.2024.11.12.08.02.stable_02\":true}",
    "ReceivedReferralTheme": "\"Inactive\"",
    "AutosuggestionAcceptedCount": "2",
    "InputMode": "\"PinnedToTop\"",
    "ForceX11": "false",
    "AIRequestLimitInfo": "{\"limit\":100,\"num_requests_used_since_refresh\":0,\"next_refresh_time\":\"2024-11-23T19:48:57.979500Z\",\"is_unlimited\":false}"
  }
}